<Properties StartupConfiguration="{2E98E4E3-5BE3-47EF-B8B1-44ABB4B87936}|Default">
  <MonoDevelop.Ide.Workbench ActiveDocument="Controllers/ClientController.cs">
    <Files>
      <File FileName="Controllers/ClientController.cs" Line="76" Column="131" />
    </Files>
  </MonoDevelop.Ide.Workbench>
  <MonoDevelop.Ide.ItemProperties.Sneakerx__mvc PreferredExecutionTarget="MonoDevelop.Default" />
  <MonoDevelop.Ide.DebuggingService.PinnedWatches />
  <MonoDevelop.Ide.Workspace ActiveConfiguration="Debug" />
  <MonoDevelop.Ide.DebuggingService.Breakpoints>
    <BreakpointStore />
  </MonoDevelop.Ide.DebuggingService.Breakpoints>
  <MultiItemStartupConfigurations />
</Properties>